cheatshh/__init__.py
cheatshh/cheats.sh
cheatshh/cheatshh.toml
cheatshh/commands.json
cheatshh/groups.json
cheatshh/main.py
cheatshh-1.1.1.dist-info/LICENSE
cheatshh-1.1.1.dist-info/METADATA
cheatshh-1.1.1.dist-info/WHEEL
cheatshh-1.1.1.dist-info/entry_points.txt
cheatshh-1.1.1.dist-info/RECORD
