Metadata-Version: 2.1
Name: cheatshh
Version: 1.1.1
Summary: Interactive CLI for managing command line cheatsheets, written in shell script.
Home-page: https://github.com/AnirudhG07/cheatshh
Keywords: cheatsheet,cheat,command-line,CLI,shell-script
Author: Anirudh Gupta
Requires-Python: >=3.9,<4.0
Classifier: Development Status :: 5 - Production/Stable
Classifier: Intended Audience :: Developers
Classifier: License :: OSI Approved :: Apache Software License
Classifier: Operating System :: MacOS
Classifier: Operating System :: POSIX
Classifier: Programming Language :: Python :: 3
Classifier: Programming Language :: Python :: 3.9
Classifier: Programming Language :: Python :: 3.10
Classifier: Programming Language :: Python :: 3.11
Classifier: Programming Language :: Python :: 3.12
Classifier: Topic :: System :: Shells
Requires-Dist: fuzzyfinder (>=2.0.0,<3.0.0)
Requires-Dist: whiptail (>=0.2.0,<0.3.0)
